read_source/__init__.py
read_source-0.0.2.dist-info/WHEEL
read_source-0.0.2.dist-info/METADATA
read_source-0.0.2.dist-info/RECORD
