Metadata-Version: 2.1
Name: read-source
Version: 0.0.2
Summary: 
Author: Trim21
Author-email: i@trim21.me
Requires-Python: >=3.5,<4.0
Classifier: Programming Language :: Python :: 3
Classifier: Programming Language :: Python :: 3.5
Classifier: Programming Language :: Python :: 3.6
Classifier: Programming Language :: Python :: 3.7
